gspread_asyncio/__init__.py
gspread_asyncio-1.9.0.dist-info/LICENSE
gspread_asyncio-1.9.0.dist-info/METADATA
gspread_asyncio-1.9.0.dist-info/WHEEL
gspread_asyncio-1.9.0.dist-info/top_level.txt
gspread_asyncio-1.9.0.dist-info/RECORD
