Metadata-Version: 2.1
Name: gspread-asyncio
Version: 1.9.0
Summary: asyncio wrapper for burnash's Google Spreadsheet API library, gspread
Home-page: https://github.com/dgilman/gspread_asyncio
Author: David Gilman
Author-email: dgilman@gilslotd.com
License: MIT
Project-URL: Documentation, https://gspread-asyncio.readthedocs.io/en/latest/
Project-URL: Source, https://github.com/dgilman/gspread_asyncio
Project-URL: Tracker, https://github.com/dgilman/gspread_asyncio/issues
Keywords: spreadsheets,google-spreadsheets,asyncio
Classifier: Development Status :: 5 - Production/Stable
Classifier: Framework :: AsyncIO
Classifier: Intended Audience :: Developers
Classifier: License :: OSI Approved :: MIT License
Classifier: Programming Language :: Python
Classifier: Programming Language :: Python :: 3
Classifier: Programming Language :: Python :: 3 :: Only
Requires-Python: >=3.7
License-File: LICENSE
